eqator/MANIFEST.in
eqator/README.md
eqator/__init__.py
eqator/apps.py
eqator/checks.py
eqator/colors.py
eqator/constants.py
eqator/helpers.py
eqator/main.py
eqator/setup.py
eqator/__pycache__/__init__.cpython-38.pyc
eqator/__pycache__/checks.cpython-38.pyc
eqator/__pycache__/colors.cpython-38.pyc
eqator/__pycache__/constants.cpython-38.pyc
eqator/__pycache__/helpers.cpython-38.pyc
eqator/__pycache__/main.cpython-38.pyc
eqator/management/__init__.py
eqator/management/__pycache__/__init__.cpython-38.pyc
eqator/management/commands/__init__.py
eqator/management/commands/qa.py
eqator/management/commands/__pycache__/__init__.cpython-38.pyc
eqator/management/commands/__pycache__/qa.cpython-38.pyc
eqator/services/__init__.py
eqator/services/send.py
eqator/services/__pycache__/__init__.cpython-38.pyc
eqator/services/__pycache__/send.cpython-38.pyc
eqator-2.7.0.dist-info/METADATA
eqator-2.7.0.dist-info/WHEEL
eqator-2.7.0.dist-info/top_level.txt
eqator-2.7.0.dist-info/RECORD
